{
  "schemaVersion": "1.0",
  "name": "test-out\\test-sdsm",
  "variables": [
    {
      "id": "0",
      "simpleName": "testENRE",
      "qualifiedName": "depExtract.testENRE",
      "parentId": 1,
      "childrenIds": {},
      "relations": {},
      "ignore": true,
      "flag": true,
      "draggable": true,
      "category": "Method",
      "fullPath": "F:/depExtract/testENRE"
    },
    {
      "id": "1",
      "simpleName": "depExtract",
      "qualifiedName": "depExtract",
      "parentId": -1,
      "childrenIds": {},
      "relations": {},
      "ignore": true,
      "flag": true,
      "draggable": true,
      "category": "Method",
      "fullPath": "F:/depExtract"
    }
  ],
  "cells": [
    {
      "source": "0",
      "target": "1",
      "values": {
        "Define": 1
      }
    },
    {
      "source": "1",
      "target": "0",
      "values": {
        "Define": 1
      }
    }
  ],
  "categories": [
    {
      "name": "Module"
    },
    {
      "name": "Function"
    },
    {
      "name": "Class"
    },
    {
      "name": "Method"
    },
    {
      "name": "Variable"
    },
    {
      "name": "Parameter"
    },
    {
      "name": "Property"
    }
  ],
  "entityNum": [
    {
      "Package": 6,
      "Module": 52,
      "Function": 802,
      "Class": 67,
      "Method": 707,
      "Variable": 3448,
      "Property": 2788,
      "Parameter": 3673
    }
  ]
}